setup.py
micropython_ucurses.egg-info/PKG-INFO
micropython_ucurses.egg-info/SOURCES.txt
micropython_ucurses.egg-info/dependency_links.txt
micropython_ucurses.egg-info/requires.txt
micropython_ucurses.egg-info/top_level.txt
ucurses/__init__.py